Metadata-Version: 2.1
Name: django-rest-knox
Version: 5.0.2
Summary: Authentication for django rest framework
Home-page: https://github.com/jazzband/django-rest-knox
Author: James McMahon
Author-email: james1345@googlemail.com
License: MIT
Keywords: django rest authentication login
Classifier: Development Status :: 5 - Production/Stable
Classifier: Intended Audience :: Developers
Classifier: Topic :: Internet :: WWW/HTTP :: Session
Classifier: License :: OSI Approved :: MIT License
Classifier: Programming Language :: Python :: 3
Classifier: Programming Language :: Python :: 3.8
Classifier: Programming Language :: Python :: 3.9
Classifier: Programming Language :: Python :: 3.10
Classifier: Programming Language :: Python :: 3.11
Classifier: Programming Language :: Python :: 3.12
Requires-Python: >=3.8
License-File: LICENSE
Requires-Dist: django>=4.2
Requires-Dist: djangorestframework
Provides-Extra: dev
Provides-Extra: test
